SBuildr-0.6.4.data/scripts/sbuildr
sbuildr/__init__.py
sbuildr/logger.py
sbuildr/backends/__init__.py
sbuildr/backends/backend.py
sbuildr/backends/rbuild.py
sbuildr/dependencies/__init__.py
sbuildr/dependencies/builder.py
sbuildr/dependencies/dependency.py
sbuildr/dependencies/fetcher.py
sbuildr/dependencies/meta.py
sbuildr/dependencies/builders/__init__.py
sbuildr/dependencies/builders/sbuildr_builder.py
sbuildr/dependencies/fetchers/__init__.py
sbuildr/dependencies/fetchers/copy_fetcher.py
sbuildr/dependencies/fetchers/git_fetcher.py
sbuildr/graph/__init__.py
sbuildr/graph/graph.py
sbuildr/graph/node.py
sbuildr/misc/__init__.py
sbuildr/misc/paths.py
sbuildr/misc/utils.py
sbuildr/project/__init__.py
sbuildr/project/file_manager.py
sbuildr/project/profile.py
sbuildr/project/project.py
sbuildr/project/target.py
sbuildr/tools/__init__.py
sbuildr/tools/compiler.py
sbuildr/tools/flags.py
sbuildr/tools/linker.py
sbuildr/tools/utils.py
SBuildr-0.6.4.dist-info/LICENSE.txt
SBuildr-0.6.4.dist-info/METADATA
SBuildr-0.6.4.dist-info/WHEEL
SBuildr-0.6.4.dist-info/top_level.txt
SBuildr-0.6.4.dist-info/zip-safe
SBuildr-0.6.4.dist-info/RECORD
