Metadata-Version: 2.1
Name: SBuildr
Version: 0.6.4
Summary: A python-based meta-build system for C++ projects.
Home-page: https://github.com/pmarathe25/SBuildr
Author: Pranav Marathe
Author-email: pmarathe25@gmail.com
License: GNU GPLv3
Platform: UNKNOWN
Classifier: License :: OSI Approved :: MIT License
Classifier: Programming Language :: Python
Classifier: Programming Language :: Python :: 3
Requires-Python: >=3
